aionanoleaf/__init__.py
aionanoleaf/events.py
aionanoleaf/exceptions.py
aionanoleaf/layout.py
aionanoleaf/nanoleaf.py
aionanoleaf/py.typed
aionanoleaf/typing.py
aionanoleaf-0.2.1.dist-info/COPYING
aionanoleaf-0.2.1.dist-info/COPYING.LESSER
aionanoleaf-0.2.1.dist-info/METADATA
aionanoleaf-0.2.1.dist-info/WHEEL
aionanoleaf-0.2.1.dist-info/top_level.txt
aionanoleaf-0.2.1.dist-info/RECORD
