Metadata-Version: 2.1
Name: aionanoleaf
Version: 0.2.1
Summary: Async Python package for the Nanoleaf API
Home-page: https://github.com/milanmeu/aionanoleaf
Author: Milan Meulemans
Author-email: milan.meulemans@live.be
License: LGPLv3+
Project-URL: Say Thanks!, https://saythanks.io/to/milan.meulemans@live.be
Project-URL: Bug Tracker, https://github.com/milanmeu/aionanoleaf/issues
Project-URL: Source Code, https://github.com/milanmeu/aionanoleaf
Project-URL: Documentation, https://github.com/milanmeu/aionanoleaf/blob/main/README.md
Keywords: nanoleaf api canvas shapes elements light panels
Classifier: Programming Language :: Python :: 3
Classifier: License :: OSI Approved :: GNU Lesser General Public License v3 or later (LGPLv3+)
Classifier: Operating System :: OS Independent
Classifier: Development Status :: 4 - Beta
Classifier: Intended Audience :: Developers
Classifier: Natural Language :: English
Classifier: Topic :: Home Automation
Classifier: Typing :: Typed
Requires-Python: >=3.8
License-File: COPYING
License-File: COPYING.LESSER
Requires-Dist: aiohttp
